checksum_checker/__init__.py
checksum_checker/__main__.py
checksum_checker/checksum_checker.py
checksum_checker-0.1.2.dist-info/LICENSE
checksum_checker-0.1.2.dist-info/METADATA
checksum_checker-0.1.2.dist-info/WHEEL
checksum_checker-0.1.2.dist-info/entry_points.txt
checksum_checker-0.1.2.dist-info/top_level.txt
checksum_checker-0.1.2.dist-info/RECORD
